{
  "ask": {
    "mgreet": ["Привет", "Здравствуй", "Хай"],
    "mhelp": ["Кто ты?", "Зачем ты?", "Как тебя зовут?"],
    "mdialog": ["Что ты можешь делать?", "Что ты умеешь?", "Что умеешь?"],
    "mquestions": ["Как настроение?", "Как погода?", "Все хорошо?"]
  },
  "answer":{
    "mgreet": ["Привет еще раз", "Еще раз здравствуйте", "Еще раз доброго времени суток"],
    "mhelp": ["Я - бот", "Я - телеграм-бот", "Я - программа, созданная человеком"],
    "mdialog": ["Пока просто поддерживать беседу", "Вести диалог", "Общаться"],
    "mquestions": ["Отлично", "Все отлично", "Замечательно"]
  }
}
